{
  "nodes": [
    {
      "id": "c_users_codec_onedrive_documents_tiniyara_theobase_worker_lib_csv_ts",
      "label": "csv.ts",
      "file_type": "code",
      "source_file": "C:\\Users\\codec\\OneDrive\\Documents\\Tiniyara\\theobase\\worker\\lib\\csv.ts",
      "source_location": "L1"
    },
    {
      "id": "lib_csv_csvparseresult",
      "label": "CsvParseResult",
      "file_type": "code",
      "source_file": "C:\\Users\\codec\\OneDrive\\Documents\\Tiniyara\\theobase\\worker\\lib\\csv.ts",
      "source_location": "L1"
    },
    {
      "id": "lib_csv_parsecsv",
      "label": "parseCsv()",
      "file_type": "code",
      "source_file": "C:\\Users\\codec\\OneDrive\\Documents\\Tiniyara\\theobase\\worker\\lib\\csv.ts",
      "source_location": "L6"
    },
    {
      "id": "lib_csv_validatecsvheaders",
      "label": "validateCsvHeaders()",
      "file_type": "code",
      "source_file": "C:\\Users\\codec\\OneDrive\\Documents\\Tiniyara\\theobase\\worker\\lib\\csv.ts",
      "source_location": "L43"
    }
  ],
  "edges": [
    {
      "source": "c_users_codec_onedrive_documents_tiniyara_theobase_worker_lib_csv_ts",
      "target": "lib_csv_csvparseresult",
      "relation": "contains",
      "confidence": "EXTRACTED",
      "source_file": "C:\\Users\\codec\\OneDrive\\Documents\\Tiniyara\\theobase\\worker\\lib\\csv.ts",
      "source_location": "L1",
      "weight": 1.0
    },
    {
      "source": "c_users_codec_onedrive_documents_tiniyara_theobase_worker_lib_csv_ts",
      "target": "lib_csv_parsecsv",
      "relation": "contains",
      "confidence": "EXTRACTED",
      "source_file": "C:\\Users\\codec\\OneDrive\\Documents\\Tiniyara\\theobase\\worker\\lib\\csv.ts",
      "source_location": "L6",
      "weight": 1.0
    },
    {
      "source": "c_users_codec_onedrive_documents_tiniyara_theobase_worker_lib_csv_ts",
      "target": "lib_csv_validatecsvheaders",
      "relation": "contains",
      "confidence": "EXTRACTED",
      "source_file": "C:\\Users\\codec\\OneDrive\\Documents\\Tiniyara\\theobase\\worker\\lib\\csv.ts",
      "source_location": "L43",
      "weight": 1.0
    }
  ],
  "raw_calls": [
    {
      "caller_nid": "lib_csv_parsecsv",
      "callee": "filter",
      "is_member_call": true,
      "source_file": "C:\\Users\\codec\\OneDrive\\Documents\\Tiniyara\\theobase\\worker\\lib\\csv.ts",
      "source_location": "L7"
    },
    {
      "caller_nid": "lib_csv_parsecsv",
      "callee": "map",
      "is_member_call": true,
      "source_file": "C:\\Users\\codec\\OneDrive\\Documents\\Tiniyara\\theobase\\worker\\lib\\csv.ts",
      "source_location": "L7"
    },
    {
      "caller_nid": "lib_csv_parsecsv",
      "callee": "split",
      "is_member_call": true,
      "source_file": "C:\\Users\\codec\\OneDrive\\Documents\\Tiniyara\\theobase\\worker\\lib\\csv.ts",
      "source_location": "L7"
    },
    {
      "caller_nid": "lib_csv_parsecsv",
      "callee": "map",
      "is_member_call": true,
      "source_file": "C:\\Users\\codec\\OneDrive\\Documents\\Tiniyara\\theobase\\worker\\lib\\csv.ts",
      "source_location": "L12"
    },
    {
      "caller_nid": "lib_csv_validatecsvheaders",
      "callee": "filter",
      "is_member_call": true,
      "source_file": "C:\\Users\\codec\\OneDrive\\Documents\\Tiniyara\\theobase\\worker\\lib\\csv.ts",
      "source_location": "L44"
    },
    {
      "caller_nid": "lib_csv_validatecsvheaders",
      "callee": "join",
      "is_member_call": true,
      "source_file": "C:\\Users\\codec\\OneDrive\\Documents\\Tiniyara\\theobase\\worker\\lib\\csv.ts",
      "source_location": "L46"
    }
  ]
}
