{
  "nodes": [
    {
      "id": "c_users_codec_onedrive_documents_tiniyara_theobase_worker_repos_reconciliation_ts",
      "label": "reconciliation.ts",
      "file_type": "code",
      "source_file": "C:\\Users\\codec\\OneDrive\\Documents\\Tiniyara\\theobase\\worker\\repos\\reconciliation.ts",
      "source_location": "L1"
    },
    {
      "id": "repos_reconciliation_receivetithedata",
      "label": "ReceiveTitheData",
      "file_type": "code",
      "source_file": "C:\\Users\\codec\\OneDrive\\Documents\\Tiniyara\\theobase\\worker\\repos\\reconciliation.ts",
      "source_location": "L5"
    },
    {
      "id": "repos_reconciliation_setbalancedata",
      "label": "SetBalanceData",
      "file_type": "code",
      "source_file": "C:\\Users\\codec\\OneDrive\\Documents\\Tiniyara\\theobase\\worker\\repos\\reconciliation.ts",
      "source_location": "L14"
    },
    {
      "id": "repos_reconciliation_conferencetitherow",
      "label": "ConferenceTitheRow",
      "file_type": "code",
      "source_file": "C:\\Users\\codec\\OneDrive\\Documents\\Tiniyara\\theobase\\worker\\repos\\reconciliation.ts",
      "source_location": "L24"
    },
    {
      "id": "repos_reconciliation_churchbalancerow",
      "label": "ChurchBalanceRow",
      "file_type": "code",
      "source_file": "C:\\Users\\codec\\OneDrive\\Documents\\Tiniyara\\theobase\\worker\\repos\\reconciliation.ts",
      "source_location": "L35"
    },
    {
      "id": "repos_reconciliation_tithereportrow",
      "label": "TitheReportRow",
      "file_type": "code",
      "source_file": "C:\\Users\\codec\\OneDrive\\Documents\\Tiniyara\\theobase\\worker\\repos\\reconciliation.ts",
      "source_location": "L42"
    },
    {
      "id": "repos_reconciliation_reconciliationrow",
      "label": "ReconciliationRow",
      "file_type": "code",
      "source_file": "C:\\Users\\codec\\OneDrive\\Documents\\Tiniyara\\theobase\\worker\\repos\\reconciliation.ts",
      "source_location": "L55"
    },
    {
      "id": "repos_reconciliation_reconciliationrepo",
      "label": "ReconciliationRepo",
      "file_type": "code",
      "source_file": "C:\\Users\\codec\\OneDrive\\Documents\\Tiniyara\\theobase\\worker\\repos\\reconciliation.ts",
      "source_location": "L57"
    },
    {
      "id": "repos_reconciliation_reconciliationrepo_constructor",
      "label": ".constructor()",
      "file_type": "code",
      "source_file": "C:\\Users\\codec\\OneDrive\\Documents\\Tiniyara\\theobase\\worker\\repos\\reconciliation.ts",
      "source_location": "L58"
    },
    {
      "id": "repos_reconciliation_reconciliationrepo_getconferencetithe",
      "label": ".getConferenceTithe()",
      "file_type": "code",
      "source_file": "C:\\Users\\codec\\OneDrive\\Documents\\Tiniyara\\theobase\\worker\\repos\\reconciliation.ts",
      "source_location": "L60"
    },
    {
      "id": "repos_reconciliation_reconciliationrepo_receivetithe",
      "label": ".receiveTithe()",
      "file_type": "code",
      "source_file": "C:\\Users\\codec\\OneDrive\\Documents\\Tiniyara\\theobase\\worker\\repos\\reconciliation.ts",
      "source_location": "L81"
    },
    {
      "id": "repos_reconciliation_reconciliationrepo_getchurchbalance",
      "label": ".getChurchBalance()",
      "file_type": "code",
      "source_file": "C:\\Users\\codec\\OneDrive\\Documents\\Tiniyara\\theobase\\worker\\repos\\reconciliation.ts",
      "source_location": "L118"
    },
    {
      "id": "repos_reconciliation_reconciliationrepo_setchurchbalance",
      "label": ".setChurchBalance()",
      "file_type": "code",
      "source_file": "C:\\Users\\codec\\OneDrive\\Documents\\Tiniyara\\theobase\\worker\\repos\\reconciliation.ts",
      "source_location": "L136"
    },
    {
      "id": "repos_reconciliation_reconciliationrepo_gettithereport",
      "label": ".getTitheReport()",
      "file_type": "code",
      "source_file": "C:\\Users\\codec\\OneDrive\\Documents\\Tiniyara\\theobase\\worker\\repos\\reconciliation.ts",
      "source_location": "L176"
    },
    {
      "id": "repos_reconciliation_reconciliationrepo_getbychurchandmonth",
      "label": ".getByChurchAndMonth()",
      "file_type": "code",
      "source_file": "C:\\Users\\codec\\OneDrive\\Documents\\Tiniyara\\theobase\\worker\\repos\\reconciliation.ts",
      "source_location": "L197"
    }
  ],
  "edges": [
    {
      "source": "c_users_codec_onedrive_documents_tiniyara_theobase_worker_repos_reconciliation_ts",
      "target": "drizzle_orm",
      "relation": "imports_from",
      "context": "import",
      "confidence": "EXTRACTED",
      "source_file": "C:\\Users\\codec\\OneDrive\\Documents\\Tiniyara\\theobase\\worker\\repos\\reconciliation.ts",
      "source_location": "L1",
      "weight": 1.0
    },
    {
      "source": "c_users_codec_onedrive_documents_tiniyara_theobase_worker_repos_reconciliation_ts",
      "target": "c_users_codec_onedrive_documents_tiniyara_theobase_worker_lib_db_ts",
      "relation": "imports_from",
      "context": "import",
      "confidence": "EXTRACTED",
      "source_file": "C:\\Users\\codec\\OneDrive\\Documents\\Tiniyara\\theobase\\worker\\repos\\reconciliation.ts",
      "source_location": "L2",
      "weight": 1.0
    },
    {
      "source": "c_users_codec_onedrive_documents_tiniyara_theobase_worker_repos_reconciliation_ts",
      "target": "lib_db_db",
      "relation": "imports",
      "context": "import",
      "confidence": "EXTRACTED",
      "source_file": "C:\\Users\\codec\\OneDrive\\Documents\\Tiniyara\\theobase\\worker\\repos\\reconciliation.ts",
      "source_location": "L2",
      "weight": 1.0
    },
    {
      "source": "c_users_codec_onedrive_documents_tiniyara_theobase_worker_repos_reconciliation_ts",
      "target": "c_users_codec_onedrive_documents_tiniyara_theobase_worker_schema_reconciliation_ts",
      "relation": "imports_from",
      "context": "import",
      "confidence": "EXTRACTED",
      "source_file": "C:\\Users\\codec\\OneDrive\\Documents\\Tiniyara\\theobase\\worker\\repos\\reconciliation.ts",
      "source_location": "L3",
      "weight": 1.0
    },
    {
      "source": "c_users_codec_onedrive_documents_tiniyara_theobase_worker_repos_reconciliation_ts",
      "target": "schema_reconciliation_reconciliations",
      "relation": "imports",
      "context": "import",
      "confidence": "EXTRACTED",
      "source_file": "C:\\Users\\codec\\OneDrive\\Documents\\Tiniyara\\theobase\\worker\\repos\\reconciliation.ts",
      "source_location": "L3",
      "weight": 1.0
    },
    {
      "source": "c_users_codec_onedrive_documents_tiniyara_theobase_worker_repos_reconciliation_ts",
      "target": "repos_reconciliation_receivetithedata",
      "relation": "contains",
      "confidence": "EXTRACTED",
      "source_file": "C:\\Users\\codec\\OneDrive\\Documents\\Tiniyara\\theobase\\worker\\repos\\reconciliation.ts",
      "source_location": "L5",
      "weight": 1.0
    },
    {
      "source": "c_users_codec_onedrive_documents_tiniyara_theobase_worker_repos_reconciliation_ts",
      "target": "repos_reconciliation_setbalancedata",
      "relation": "contains",
      "confidence": "EXTRACTED",
      "source_file": "C:\\Users\\codec\\OneDrive\\Documents\\Tiniyara\\theobase\\worker\\repos\\reconciliation.ts",
      "source_location": "L14",
      "weight": 1.0
    },
    {
      "source": "c_users_codec_onedrive_documents_tiniyara_theobase_worker_repos_reconciliation_ts",
      "target": "repos_reconciliation_conferencetitherow",
      "relation": "contains",
      "confidence": "EXTRACTED",
      "source_file": "C:\\Users\\codec\\OneDrive\\Documents\\Tiniyara\\theobase\\worker\\repos\\reconciliation.ts",
      "source_location": "L24",
      "weight": 1.0
    },
    {
      "source": "c_users_codec_onedrive_documents_tiniyara_theobase_worker_repos_reconciliation_ts",
      "target": "repos_reconciliation_churchbalancerow",
      "relation": "contains",
      "confidence": "EXTRACTED",
      "source_file": "C:\\Users\\codec\\OneDrive\\Documents\\Tiniyara\\theobase\\worker\\repos\\reconciliation.ts",
      "source_location": "L35",
      "weight": 1.0
    },
    {
      "source": "c_users_codec_onedrive_documents_tiniyara_theobase_worker_repos_reconciliation_ts",
      "target": "repos_reconciliation_tithereportrow",
      "relation": "contains",
      "confidence": "EXTRACTED",
      "source_file": "C:\\Users\\codec\\OneDrive\\Documents\\Tiniyara\\theobase\\worker\\repos\\reconciliation.ts",
      "source_location": "L42",
      "weight": 1.0
    },
    {
      "source": "c_users_codec_onedrive_documents_tiniyara_theobase_worker_repos_reconciliation_ts",
      "target": "repos_reconciliation_reconciliationrow",
      "relation": "contains",
      "confidence": "EXTRACTED",
      "source_file": "C:\\Users\\codec\\OneDrive\\Documents\\Tiniyara\\theobase\\worker\\repos\\reconciliation.ts",
      "source_location": "L55",
      "weight": 1.0
    },
    {
      "source": "c_users_codec_onedrive_documents_tiniyara_theobase_worker_repos_reconciliation_ts",
      "target": "repos_reconciliation_reconciliationrepo",
      "relation": "contains",
      "confidence": "EXTRACTED",
      "source_file": "C:\\Users\\codec\\OneDrive\\Documents\\Tiniyara\\theobase\\worker\\repos\\reconciliation.ts",
      "source_location": "L57",
      "weight": 1.0
    },
    {
      "source": "repos_reconciliation_reconciliationrepo",
      "target": "repos_reconciliation_reconciliationrepo_constructor",
      "relation": "method",
      "confidence": "EXTRACTED",
      "source_file": "C:\\Users\\codec\\OneDrive\\Documents\\Tiniyara\\theobase\\worker\\repos\\reconciliation.ts",
      "source_location": "L58",
      "weight": 1.0
    },
    {
      "source": "repos_reconciliation_reconciliationrepo",
      "target": "repos_reconciliation_reconciliationrepo_getconferencetithe",
      "relation": "method",
      "confidence": "EXTRACTED",
      "source_file": "C:\\Users\\codec\\OneDrive\\Documents\\Tiniyara\\theobase\\worker\\repos\\reconciliation.ts",
      "source_location": "L60",
      "weight": 1.0
    },
    {
      "source": "repos_reconciliation_reconciliationrepo",
      "target": "repos_reconciliation_reconciliationrepo_receivetithe",
      "relation": "method",
      "confidence": "EXTRACTED",
      "source_file": "C:\\Users\\codec\\OneDrive\\Documents\\Tiniyara\\theobase\\worker\\repos\\reconciliation.ts",
      "source_location": "L81",
      "weight": 1.0
    },
    {
      "source": "repos_reconciliation_reconciliationrepo",
      "target": "repos_reconciliation_reconciliationrepo_getchurchbalance",
      "relation": "method",
      "confidence": "EXTRACTED",
      "source_file": "C:\\Users\\codec\\OneDrive\\Documents\\Tiniyara\\theobase\\worker\\repos\\reconciliation.ts",
      "source_location": "L118",
      "weight": 1.0
    },
    {
      "source": "repos_reconciliation_reconciliationrepo",
      "target": "repos_reconciliation_reconciliationrepo_setchurchbalance",
      "relation": "method",
      "confidence": "EXTRACTED",
      "source_file": "C:\\Users\\codec\\OneDrive\\Documents\\Tiniyara\\theobase\\worker\\repos\\reconciliation.ts",
      "source_location": "L136",
      "weight": 1.0
    },
    {
      "source": "repos_reconciliation_reconciliationrepo",
      "target": "repos_reconciliation_reconciliationrepo_gettithereport",
      "relation": "method",
      "confidence": "EXTRACTED",
      "source_file": "C:\\Users\\codec\\OneDrive\\Documents\\Tiniyara\\theobase\\worker\\repos\\reconciliation.ts",
      "source_location": "L176",
      "weight": 1.0
    },
    {
      "source": "repos_reconciliation_reconciliationrepo",
      "target": "repos_reconciliation_reconciliationrepo_getbychurchandmonth",
      "relation": "method",
      "confidence": "EXTRACTED",
      "source_file": "C:\\Users\\codec\\OneDrive\\Documents\\Tiniyara\\theobase\\worker\\repos\\reconciliation.ts",
      "source_location": "L197",
      "weight": 1.0
    }
  ],
  "raw_calls": [
    {
      "caller_nid": "repos_reconciliation_reconciliationrepo_getconferencetithe",
      "callee": "all",
      "is_member_call": true,
      "source_file": "C:\\Users\\codec\\OneDrive\\Documents\\Tiniyara\\theobase\\worker\\repos\\reconciliation.ts",
      "source_location": "L63"
    },
    {
      "caller_nid": "repos_reconciliation_reconciliationrepo_getconferencetithe",
      "callee": "sql",
      "is_member_call": false,
      "source_file": "C:\\Users\\codec\\OneDrive\\Documents\\Tiniyara\\theobase\\worker\\repos\\reconciliation.ts",
      "source_location": "L64"
    },
    {
      "caller_nid": "repos_reconciliation_reconciliationrepo_receivetithe",
      "callee": "await this.db\n      .get",
      "is_member_call": false,
      "source_file": "C:\\Users\\codec\\OneDrive\\Documents\\Tiniyara\\theobase\\worker\\repos\\reconciliation.ts",
      "source_location": "L82"
    },
    {
      "caller_nid": "repos_reconciliation_reconciliationrepo_receivetithe",
      "callee": "sql",
      "is_member_call": false,
      "source_file": "C:\\Users\\codec\\OneDrive\\Documents\\Tiniyara\\theobase\\worker\\repos\\reconciliation.ts",
      "source_location": "L84"
    },
    {
      "caller_nid": "repos_reconciliation_reconciliationrepo_receivetithe",
      "callee": "get",
      "is_member_call": true,
      "source_file": "C:\\Users\\codec\\OneDrive\\Documents\\Tiniyara\\theobase\\worker\\repos\\reconciliation.ts",
      "source_location": "L91"
    },
    {
      "caller_nid": "repos_reconciliation_reconciliationrepo_receivetithe",
      "callee": "sql",
      "is_member_call": false,
      "source_file": "C:\\Users\\codec\\OneDrive\\Documents\\Tiniyara\\theobase\\worker\\repos\\reconciliation.ts",
      "source_location": "L93"
    },
    {
      "caller_nid": "repos_reconciliation_reconciliationrepo_receivetithe",
      "callee": "get",
      "is_member_call": true,
      "source_file": "C:\\Users\\codec\\OneDrive\\Documents\\Tiniyara\\theobase\\worker\\repos\\reconciliation.ts",
      "source_location": "L104"
    },
    {
      "caller_nid": "repos_reconciliation_reconciliationrepo_receivetithe",
      "callee": "sql",
      "is_member_call": false,
      "source_file": "C:\\Users\\codec\\OneDrive\\Documents\\Tiniyara\\theobase\\worker\\repos\\reconciliation.ts",
      "source_location": "L106"
    },
    {
      "caller_nid": "repos_reconciliation_reconciliationrepo_getchurchbalance",
      "callee": "get",
      "is_member_call": true,
      "source_file": "C:\\Users\\codec\\OneDrive\\Documents\\Tiniyara\\theobase\\worker\\repos\\reconciliation.ts",
      "source_location": "L123"
    },
    {
      "caller_nid": "repos_reconciliation_reconciliationrepo_getchurchbalance",
      "callee": "sql",
      "is_member_call": false,
      "source_file": "C:\\Users\\codec\\OneDrive\\Documents\\Tiniyara\\theobase\\worker\\repos\\reconciliation.ts",
      "source_location": "L124"
    },
    {
      "caller_nid": "repos_reconciliation_reconciliationrepo_setchurchbalance",
      "callee": "await this.db\n      .get",
      "is_member_call": false,
      "source_file": "C:\\Users\\codec\\OneDrive\\Documents\\Tiniyara\\theobase\\worker\\repos\\reconciliation.ts",
      "source_location": "L139"
    },
    {
      "caller_nid": "repos_reconciliation_reconciliationrepo_setchurchbalance",
      "callee": "sql",
      "is_member_call": false,
      "source_file": "C:\\Users\\codec\\OneDrive\\Documents\\Tiniyara\\theobase\\worker\\repos\\reconciliation.ts",
      "source_location": "L141"
    },
    {
      "caller_nid": "repos_reconciliation_reconciliationrepo_setchurchbalance",
      "callee": "get",
      "is_member_call": true,
      "source_file": "C:\\Users\\codec\\OneDrive\\Documents\\Tiniyara\\theobase\\worker\\repos\\reconciliation.ts",
      "source_location": "L148"
    },
    {
      "caller_nid": "repos_reconciliation_reconciliationrepo_setchurchbalance",
      "callee": "sql",
      "is_member_call": false,
      "source_file": "C:\\Users\\codec\\OneDrive\\Documents\\Tiniyara\\theobase\\worker\\repos\\reconciliation.ts",
      "source_location": "L150"
    },
    {
      "caller_nid": "repos_reconciliation_reconciliationrepo_setchurchbalance",
      "callee": "get",
      "is_member_call": true,
      "source_file": "C:\\Users\\codec\\OneDrive\\Documents\\Tiniyara\\theobase\\worker\\repos\\reconciliation.ts",
      "source_location": "L162"
    },
    {
      "caller_nid": "repos_reconciliation_reconciliationrepo_setchurchbalance",
      "callee": "sql",
      "is_member_call": false,
      "source_file": "C:\\Users\\codec\\OneDrive\\Documents\\Tiniyara\\theobase\\worker\\repos\\reconciliation.ts",
      "source_location": "L164"
    },
    {
      "caller_nid": "repos_reconciliation_reconciliationrepo_gettithereport",
      "callee": "all",
      "is_member_call": true,
      "source_file": "C:\\Users\\codec\\OneDrive\\Documents\\Tiniyara\\theobase\\worker\\repos\\reconciliation.ts",
      "source_location": "L177"
    },
    {
      "caller_nid": "repos_reconciliation_reconciliationrepo_gettithereport",
      "callee": "sql",
      "is_member_call": false,
      "source_file": "C:\\Users\\codec\\OneDrive\\Documents\\Tiniyara\\theobase\\worker\\repos\\reconciliation.ts",
      "source_location": "L178"
    },
    {
      "caller_nid": "repos_reconciliation_reconciliationrepo_getbychurchandmonth",
      "callee": "get",
      "is_member_call": true,
      "source_file": "C:\\Users\\codec\\OneDrive\\Documents\\Tiniyara\\theobase\\worker\\repos\\reconciliation.ts",
      "source_location": "L202"
    },
    {
      "caller_nid": "repos_reconciliation_reconciliationrepo_getbychurchandmonth",
      "callee": "where",
      "is_member_call": true,
      "source_file": "C:\\Users\\codec\\OneDrive\\Documents\\Tiniyara\\theobase\\worker\\repos\\reconciliation.ts",
      "source_location": "L202"
    },
    {
      "caller_nid": "repos_reconciliation_reconciliationrepo_getbychurchandmonth",
      "callee": "from",
      "is_member_call": true,
      "source_file": "C:\\Users\\codec\\OneDrive\\Documents\\Tiniyara\\theobase\\worker\\repos\\reconciliation.ts",
      "source_location": "L202"
    },
    {
      "caller_nid": "repos_reconciliation_reconciliationrepo_getbychurchandmonth",
      "callee": "select",
      "is_member_call": true,
      "source_file": "C:\\Users\\codec\\OneDrive\\Documents\\Tiniyara\\theobase\\worker\\repos\\reconciliation.ts",
      "source_location": "L202"
    },
    {
      "caller_nid": "repos_reconciliation_reconciliationrepo_getbychurchandmonth",
      "callee": "and",
      "is_member_call": false,
      "source_file": "C:\\Users\\codec\\OneDrive\\Documents\\Tiniyara\\theobase\\worker\\repos\\reconciliation.ts",
      "source_location": "L206"
    },
    {
      "caller_nid": "repos_reconciliation_reconciliationrepo_getbychurchandmonth",
      "callee": "eq",
      "is_member_call": false,
      "source_file": "C:\\Users\\codec\\OneDrive\\Documents\\Tiniyara\\theobase\\worker\\repos\\reconciliation.ts",
      "source_location": "L207"
    },
    {
      "caller_nid": "repos_reconciliation_reconciliationrepo_getbychurchandmonth",
      "callee": "eq",
      "is_member_call": false,
      "source_file": "C:\\Users\\codec\\OneDrive\\Documents\\Tiniyara\\theobase\\worker\\repos\\reconciliation.ts",
      "source_location": "L208"
    },
    {
      "caller_nid": "repos_reconciliation_reconciliationrepo_getbychurchandmonth",
      "callee": "eq",
      "is_member_call": false,
      "source_file": "C:\\Users\\codec\\OneDrive\\Documents\\Tiniyara\\theobase\\worker\\repos\\reconciliation.ts",
      "source_location": "L209"
    }
  ]
}
